aiopjlink/__init__.py
aiopjlink/cli.py
aiopjlink/cli2.py
aiopjlink/projector.py
test/__init__.py
test/test_projector.py
aiopjlink_kw-1.0.5.dist-info/WHEEL
aiopjlink_kw-1.0.5.dist-info/METADATA
aiopjlink_kw-1.0.5.dist-info/licenses/LICENSE
aiopjlink_kw-1.0.5.dist-info/RECORD
