Metadata-Version: 2.1
Name: aiopjlink-kw
Version: 1.0.5
Summary: Asyncio PJLink library (Class 1 and Class 2)
License: MIT
Keywords: projector,pjlink,asyncio
Author-email: HE Inventions LTD <support@heinventions.com>,Uladzimir Kazakevich <kwull@kwull.com>
Requires-Python: >=3.9
Classifier: Framework :: AsyncIO
Classifier: License :: OSI Approved :: MIT License
Classifier: Operating System :: OS Independent
Classifier: Programming Language :: Python :: 3
Project-URL: Bug Tracker, https://github.com/kwull/aiopjlink/issues
Project-URL: Homepage, https://pypi.org/project/aiopjlink-kw/
Project-URL: Repository, https://github.com/kwull/aiopjlink
